d1_util/__init__.py
d1_util/cert_check_cn.py
d1_util/cert_check_local.py
d1_util/cert_create_ca.py
d1_util/cert_create_csr.py
d1_util/cert_sign_csr.py
d1_util/check_object_checksums.py
d1_util/check_scimeta_indexing.py
d1_util/check_x509_certificate_cn.py
d1_util/check_x509_certificate_local.py
d1_util/compare_object_lists.py
d1_util/create_data_packages.py
d1_util/create_object_on_member_node.py
d1_util/delete_all_objects_of_type.py
d1_util/display_node_status.py
d1_util/download_all_objects.py
d1_util/download_and_display_data_package.py
d1_util/download_mn_objects.py
d1_util/download_sciobj.py
d1_util/download_server_certs.py
d1_util/download_sysmeta.py
d1_util/download_sysmeta_multiproc.py
d1_util/download_test_docs.py
d1_util/find_gmn_instances.py
d1_util/find_node_versions.py
d1_util/generate_data_package_from_stream.py
d1_util/generate_object_stats.py
d1_util/generate_sysmeta.py
d1_util/generate_test_subject_certs.py
d1_util/jwt_token_tasks.py
d1_util/parse_format_id_list.py
d1_util/resolve_package_identifier.py
d1_util/solr_query.py
d1_util/validate_system_metadata.py
d1_util/xml_apply_xslt.py
d1_util/xml_remove_empty_elements.py
d1_util/xml_strip_whitespace.py
d1_util/tests/__init__.py
d1_util/tests/test_cert.py
dataone.util-3.5.2.dist-info/METADATA
dataone.util-3.5.2.dist-info/WHEEL
dataone.util-3.5.2.dist-info/entry_points.txt
dataone.util-3.5.2.dist-info/top_level.txt
dataone.util-3.5.2.dist-info/RECORD
